iot_inspector_client/__init__.py
iot_inspector_client/client.py
iot_inspector_client/errors.py
iot_inspector_client/keys/__init__.py
iot_inspector_client/keys/ca.pem
iot_inspector_client/models.py
iot_inspector_client/queries/__init__.py
iot_inspector_client/queries/create_firmware_upload.graphql
iot_inspector_client/queries/utils.py
iot_inspector_client-1.2.1.dist-info/LICENSE
iot_inspector_client-1.2.1.dist-info/WHEEL
iot_inspector_client-1.2.1.dist-info/METADATA
iot_inspector_client-1.2.1.dist-info/RECORD
