Metadata-Version: 2.1
Name: iot-inspector-client
Version: 1.2.1
Summary: IoT Inspector API client
Home-page: https://www.iot-inspector.com/
License: MIT
Keywords: iot,security,firmware,analysis
Author: IoT Inspector
Author-email: support@iot-inspector.com
Requires-Python: >=3.6.2,<4.0.0
Classifier: Development Status :: 4 - Beta
Classifier: Environment :: Console
Classifier: License :: OSI Approved :: MIT License
Classifier: Operating System :: OS Independent
Classifier: Programming Language :: Python :: 3
Classifier: Programming Language :: Python :: 3 :: Only
Classifier: Programming Language :: Python :: 3.10
Classifier: Programming Language :: Python :: 3.7
Classifier: Programming Language :: Python :: 3.8
Classifier: Programming Language :: Python :: 3.9
Classifier: Topic :: Security
Requires-Dist: Authlib (>=0.15.3,<0.16.0)
Requires-Dist: httpx (>=0.17.0,<0.18.0)
Requires-Dist: importlib-resources (>=5.1.2,<6.0.0)
Requires-Dist: pydantic (==1.8.2)
Project-URL: Bug Tracker, https://github.com/IoT-Inspector/python-client/issues
Project-URL: GitHub, https://github.com/IoT-Inspector/python-client
